xtwine/__init__.py
xtwine/_version.py
xtwine/algo.py
xtwine/cli.py
xtwine/twine.py
xtwine-1.0.2.dist-info/METADATA
xtwine-1.0.2.dist-info/WHEEL
xtwine-1.0.2.dist-info/entry_points.txt
xtwine-1.0.2.dist-info/top_level.txt
xtwine-1.0.2.dist-info/RECORD
