Metadata-Version: 2.1
Name: xtwine
Version: 1.0.2
Summary: UNKNOWN
Home-page: https://github.com/amoallim15/xtwine
Author: Ali Moallim
Author-email: amoallim15@gmail.com
License: MIT
Keywords: twine cipher encryption decryption
Platform: all
Classifier: Environment :: Console
Classifier: Intended Audience :: Developers
Classifier: Operating System :: OS Independent
Classifier: Programming Language :: Python
Classifier: Programming Language :: Python :: 2
Classifier: Programming Language :: Python :: 2.7
Classifier: Programming Language :: Python :: 3
Classifier: Programming Language :: Python :: 3.4
Classifier: Programming Language :: Python :: 3.5
Classifier: Programming Language :: Python :: 3.6
Classifier: Programming Language :: Python :: 3.7
Classifier: Programming Language :: Python :: 3.8
